pypipq/__init__.py
pypipq/cli.py
pypipq/core/__init__.py
pypipq/core/base_validator.py
pypipq/core/config.py
pypipq/core/validator.py
pypipq/utils/__init__.py
pypipq/utils/cache_manager.py
pypipq/utils/environment.py
pypipq/utils/pypi.py
pypipq/utils/vulnerability_db.py
pypipq/validators/__init__.py
pypipq/validators/age.py
pypipq/validators/cryptographic_validator.py
pypipq/validators/dependency_validator.py
pypipq/validators/expired_domains_validator.py
pypipq/validators/gpg_validator.py
pypipq/validators/integrity_validator.py
pypipq/validators/license_validator.py
pypipq/validators/maintainer.py
pypipq/validators/malware_detector.py
pypipq/validators/new_bin_validator.py
pypipq/validators/popularity_validator.py
pypipq/validators/provenance_validator.py
pypipq/validators/release_age_validator.py
pypipq/validators/scripts_validator.py
pypipq/validators/signatures_validator.py
pypipq/validators/size_validator.py
pypipq/validators/source_validator.py
pypipq/validators/static_analysis_validator.py
pypipq/validators/typosquat.py
pypipq/validators/vulnerability_validator.py
pypipq-0.3.0.dist-info/METADATA
pypipq-0.3.0.dist-info/WHEEL
pypipq-0.3.0.dist-info/entry_points.txt
pypipq-0.3.0.dist-info/licenses/LICENSE
pypipq-0.3.0.dist-info/RECORD
