Metadata-Version: 2.4
Name: pypipq
Version: 0.3.0
Summary: A secure pip proxy that analyzes Python packages before installation to detect potential security issues and risks.
Project-URL: Homepage, https://github.com/livrasand/pipq
Project-URL: Repository, https://github.com/livrasand/pipq
Project-URL: Issues, https://github.com/livrasand/pipq/issues
Author-email: Livrädo Sandoval <livrasand@outlook.com>
License:                     GNU GENERAL PUBLIC LICENSE
License-File: LICENSE
Keywords: installation,package,pip,proxy,security,vulnerability
Classifier: Development Status :: 3 - Alpha
Classifier: Intended Audience :: Developers
Classifier: License :: OSI Approved :: GNU General Public License v3 (GPLv3)
Classifier: Programming Language :: Python :: 3
Classifier: Programming Language :: Python :: 3.8
Classifier: Programming Language :: Python :: 3.9
Classifier: Programming Language :: Python :: 3.10
Classifier: Programming Language :: Python :: 3.11
Classifier: Programming Language :: Python :: 3.12
Classifier: Topic :: Security
Classifier: Topic :: Software Development :: Libraries :: Python Modules
Classifier: Topic :: System :: Installation/Setup
Requires-Python: >=3.8
Requires-Dist: beautifulsoup4>=4.9.3
Requires-Dist: bloom-filter2
Requires-Dist: click>=8.0.0
Requires-Dist: google>=3.0.0
Requires-Dist: halo>=0.0.31
Requires-Dist: packaging>=21.0
Requires-Dist: portalocker>=2.0.0
Requires-Dist: python-gnupg>=0.5.5
Requires-Dist: python-whois>=0.9.5
Requires-Dist: requests>=2.25.0
Requires-Dist: rich>=13.0.0
Requires-Dist: toml>=0.10.2
Requires-Dist: tomli-w>=1.0.0
Requires-Dist: tomli>=1.2.0; python_version < '3.11'
Provides-Extra: dev
Requires-Dist: black>=23.0.0; extra == 'dev'
Requires-Dist: flake8>=6.0.0; extra == 'dev'
Requires-Dist: mypy>=1.0.0; extra == 'dev'
Requires-Dist: pytest-cov>=4.0.0; extra == 'dev'
Requires-Dist: pytest-mock>=3.10.0; extra == 'dev'
Requires-Dist: pytest>=7.0.0; extra == 'dev'
